{
  "version": "1.0",
  "project": "neon Protocol MVP - Manufacturing expert knowledge network",
  "lastUpdated": "2026-04-01T21:15:00Z",
  "features": [
    {
      "id": "F010",
      "category": "ui-core",
      "description": "3个核心页面实现(Lading、澄清、市场) + 注册流程",
      "priority": "high",
      "steps": [
        "✅ Landing 页（需求输入）",
        "✅ AI 澄清页（逐步提问）",
        "✅ agent 市场页（匹配展示)",
        "✅ 注册选择页（身份选择）",
        "✅ 需方注册页（2步骤）",
        "✅ 专家注册页（3步骤) - 部分完成",
        "深色科技风格设计",
        "✅ 响应式布局"
      ],
      "passes": true,
      "lastChecked": "2026-04-01T21:15:00Z",
      "testResults": {
        "unit": true,
        "integration": false,
        "e2e": true
      },
      "notes": "已完成 3个核心页面和注册流程（需方、专家)。后端 API 和数据库集成待完成。"
    },
    {
      "id": "F002",
      "category": "task-management",
      "description": "需求方创建任务",
      "priority": "high",
      "steps": [
        "填写任务标题和描述",
        "选择行业和地区标签",
        "设定预算和交付时间",
        "选择交付模板",
        "提交任务触发匹配"
      ],
      "passes": false,
      "lastChecked": null,
      "testResults": {
        "unit": false,
        "integration": false,
        "e2e": false
      }
    },
    {
      "id": "F003",
      "category": "matching",
      "description": "平台匹配专家 Agent",
      "priority": "high",
      "steps": [
        "基于标签筛选专家",
        "计算匹配度分数",
        "返回候选列表（1-5个）",
        "展示专家卡片"
      ],
      "passes": false,
      "lastChecked": null,
      "testResults": {
        "unit": false,
        "integration": false,
        "e2e": false
      }
    },
    {
      "id": "F004",
      "category": "order-management",
      "description": "需求方选择专家并确认订单",
      "priority": "high",
      "steps": [
        "查看匹配结果",
        "选择一个专家",
        "确认任务摘要",
        "冻结资金（模拟)",
        "生成订单"
      ],
      "passes": false,
      "lastChecked": null,
      "testResults": {
        "unit": false,
        "integration": false,
        "e2e": false
      }
    },
    {
      "id": "F005",
      "category": "order-management",
      "description": "专家接单或拒单",
      "priority": "high",
      "steps": [
        "专家接收任务通知",
        "查看任务详情",
        "评估能否回答",
        "接单：锁定保证金",
        "拒单：提交理由"
      ],
      "passes": false,
      "lastChecked": null,
      "testResults": {
        "unit": false,
        "integration": false,
        "e2e": false
      }
    },
    {
      "id": "F006",
      "category": "delivery",
      "description": "专家提交交付成果",
      "priority": "high",
      "steps": [
        "填写执行摘要",
        "填写核心结论",
        "逐问题回答",
        "填写风险与假设",
        "提交交付物"
      ],
      "passes": false,
      "lastChecked": null,
      "testResults": {
        "unit": false,
        "integration": false,
        "e2e": false
      }
    },
    {
      "id": "F007",
      "category": "review",
      "description": "平台初步审核",
      "priority": "high",
      "steps": [
        "格式完整性检查",
        "问题覆盖检查",
        "有效性检查",
        "通过或退回"
      ],
      "passes": false,
      "lastChecked": null,
      "testResults": {
        "unit": false,
        "integration": false,
        "e2e": false
      }
    },
    {
      "id": "F008",
      "category": "review",
      "description": "需求方验收交付",
      "priority": "high",
      "steps": [
        "查看交付物",
        "可选评分",
        "验收通过或要求修改",
        "确认解锁资金"
      ],
      "passes": false,
      "lastChecked": null,
      "testResults": {
        "unit": false,
        "integration": false,
        "e2e": false
      }
    },
    {
      "id": "F009",
      "category": "payment",
      "description": "资金流转（模拟托管)",
      "priority": "medium",
      "steps": [
        "需求方充值（模拟)",
        "任务资金锁定",
        "专家保证金锁定",
        "任务完成释放资金",
        "异常情况退款"
      ],
      "passes": false,
      "lastChecked": null,
      "testResults": {
        "unit": false,
        "integration": false,
        "e2e": false
      }
    },
    {
      "id": "F011",
      "category": "ui-dashboard",
      "description": "控制台页面（需求方/专家)",
      "priority": "medium",
      "steps": [
        "需求方控制台（任务列表、统计）",
        "专家控制台（订单列表、收益）",
        "钱包页面（余额、流水）",
        "订单详情页"
      ],
      "passes": false,
      "lastChecked": null,
      "testResults": {
        "unit": false,
        "integration": false,
        "e2e": false
      }
    },
    {
      "id": "F012",
      "category": "backend-api",
      "description": "后端 API(Prisma + SQLite)",
      "priority": "high",
      "steps": [
        "✅ Prisma schema 定义(Organization、Agent、Task、 order) - 完成",
        "⏳ REST API 端点(CRUD) - 待实现",
        "⏳ 状态机实现 - 待实现",
        "⏳ 资金台账系统 - 待实现"
      ],
      "passes": false,
      "lastChecked": "2026-04-01T21:15:00Z",
      "testResults": {
        "unit": true,
        "integration": false,
        "e2e": false
      },
      "notes": "Prisma schema defined, API endpoints to next sprint"
    }
  ],
  "sprints": [
    {
      "id": "Sprint-01",
      "title": "项目基础设施",
      "features": ["F010"],
      "status": "completed"
    },
    {
      "id": "Sprint-02",
      "title": "用户注册流程",
      "features": ["F001"],
      "status": "in-progress"
    },
    {
      "id": "Sprint-03",
      "title": "任务创建与匹配",
      "features": ["F002", "F003"],
      "status": "not-started"
    },
    {
      "id": "Sprint-04",
      "title": "订单与接单流程",
      "features": ["F004", "F005"],
      "status": "not-started"
    },
    {
      "id": "Sprint-05",
      "title": "交付与审核",
      "features": ["F006", "F007", "F008"],
      "status": "not-started"
    },
    {
      "id": "Sprint-06",
      "title": "资金流转",
      "features": ["F009"],
      "status": "not-started"
    },
    {
      "id": "Sprint-07",
      "title": "控制台与后端",
      "features": ["F011", "F012"],
      "status": "not-started"
    }
  ]
}
